corpca/__init__.py
corpca/corpca.py
corpca/pca.py
corpca-0.1.1.dist-info/WHEEL
corpca-0.1.1.dist-info/METADATA
corpca-0.1.1.dist-info/RECORD
