Metadata-Version: 2.1
Name: corpca
Version: 0.1.1
Summary: 
License: MIT
Author: Aiga SUZUKI
Author-email: tochikuji@gmail.com
Requires-Python: >=3.8,<4.0
Classifier: License :: OSI Approved :: MIT License
Classifier: Programming Language :: Python :: 3
Classifier: Programming Language :: Python :: 3.8
Classifier: Programming Language :: Python :: 3.9
Requires-Dist: numpy (>=1.21.2,<2.0.0)
Requires-Dist: scikit-learn (>=0.24.2,<0.25.0)
